imaris_ims_file_reader/__init__.py
imaris_ims_file_reader/_version.py
imaris_ims_file_reader/ims.py
imaris_ims_file_reader/ims_zarr_store.py
imaris_ims_file_reader/_tests/__init__.py
imaris_ims_file_reader/_tests/test_imsClass.py
imaris_ims_file_reader-0.1.8.dist-info/LICENCE
imaris_ims_file_reader-0.1.8.dist-info/METADATA
imaris_ims_file_reader-0.1.8.dist-info/WHEEL
imaris_ims_file_reader-0.1.8.dist-info/top_level.txt
imaris_ims_file_reader-0.1.8.dist-info/RECORD
