Metadata-Version: 2.1
Name: imaris-ims-file-reader
Version: 0.1.8
Summary: Class for reading Bitplane imaris files (*.ims)
Home-page: https://github.com/CBI-PITT/imaris_ims_file_reader
Author: Alan M Watson
Author-email: alan.watson@pitt.edu
License: BSD-3-Clause
Project-URL: Bug Tracker, https://github.com/CBI-PITT/imaris_ims_file_reader/issues
Project-URL: Documentation, https://github.com/CBI-PITT/imaris_ims_file_reader#README.md
Project-URL: Source Code, https://github.com/CBI-PITT/imaris_ims_file_reader
Project-URL: User Support, https://github.com/CBI-PITT/imaris_ims_file_reader/issues
Classifier: Development Status :: 2 - Pre-Alpha
Classifier: Intended Audience :: Developers
Classifier: Topic :: Software Development :: Testing
Classifier: Programming Language :: Python
Classifier: Programming Language :: Python :: 3
Classifier: Programming Language :: Python :: 3.7
Classifier: Programming Language :: Python :: 3.8
Classifier: Programming Language :: Python :: 3.9
Classifier: Operating System :: OS Independent
Classifier: License :: OSI Approved :: BSD License
Requires-Python: >=3.7
License-File: LICENCE
Requires-Dist: numpy
Requires-Dist: h5py (>=3.5.0)
Requires-Dist: scikit-image
Requires-Dist: zarr
